plasflow/__init__.py
plasflow-1.1.0.data/scripts/PlasFlow.py
plasflow-1.1.0.dist-info/DESCRIPTION.rst
plasflow-1.1.0.dist-info/METADATA
plasflow-1.1.0.dist-info/RECORD
plasflow-1.1.0.dist-info/WHEEL
plasflow-1.1.0.dist-info/dependency_links.txt
plasflow-1.1.0.dist-info/metadata.json
plasflow-1.1.0.dist-info/top_level.txt
