Metadata-Version: 2.0
Name: plasflow
Version: 1.1.0
Summary: PlasFlow - predicting plasmid sequences in metagenomic data
Home-page: https://github.com/smaegol/PlasFlow
Author: Pawel Krawczyk
Author-email: p.krawczyk@ibb.waw.pl
License: GPLv3+
Keywords: plasmid metagenome genome signature ML
Platform: UNKNOWN
Classifier: Development Status :: 5 - Production/Stable
Classifier: Intended Audience :: Science/Research
Classifier: Topic :: Scientific/Engineering :: Bio-Informatics
Classifier: Environment :: Console
Classifier: License :: OSI Approved :: GNU General Public License v3 or later (GPLv3+)
Classifier: Programming Language :: Python :: 3
Classifier: Programming Language :: Python :: 3.5
Classifier: Programming Language :: Python :: 3.6
Classifier: Operating System :: POSIX
Requires-Dist: biopython
Requires-Dist: numpy
Requires-Dist: pandas
Requires-Dist: rpy2
Requires-Dist: scikit-learn
Requires-Dist: scipy
